<?xml version="1.0" encoding="UTF-8" standalone="yes"?>

<!--
<channels>

	<channel>
		<name>CBs</name>
		<thumbnail>http://community-links.googlecode.com/svn/icons/cb.png</thumbnail>
		<items> 	

			<item>
				<title>27.235 MHz / Zierikzee / Netherlands</title>
				<link>http://82.95.218.110:8000</link>
				<link>http://yp.shoutcast.com/sbin/tunein-station.pls?id=665775</link>
				<thumbnail>https://www.cia.gov/library/publications/the-world-factbook/graphics/flags/large/nl-lgflag.gif</thumbnail>
			</item>
		  
			<item>
				<title>18ET002 Jims Radio Shack 27.555MHz / Greece</title>
				<link>http://94.68.232.186:8000</link>
				<link>http://yp.shoutcast.com/sbin/tunein-station.pls?id=2251253</link>
				<thumbnail>http://whois.domaintools.com/images/flags/gr.gif</thumbnail>
			</item>

			<item>
				<title>27.88125Mhz / 446.09375Mhz / United Kingdom / Streamed from FRN Client</title>
				<link>http://cbradio2321.no-ip.org:1010</link>
				<thumbnail>http://whois.domaintools.com/images/flags/uk.gif</thumbnail>
			</item>